ily_cli/__init__.py
ily_cli/main.py
ily_cli-0.1.1.dist-info/licenses/LICENSE
ily_cli-0.1.1.dist-info/METADATA
ily_cli-0.1.1.dist-info/WHEEL
ily_cli-0.1.1.dist-info/entry_points.txt
ily_cli-0.1.1.dist-info/top_level.txt
ily_cli-0.1.1.dist-info/RECORD
